[
  {
    "address": "TAYhjpL8pPs8T84FSM329nffQpc6jD8GBM",
    "name": "Grinex;Obshchestvo S Ogranichennoi Otvetstvennostyu Grineks"
  },
  {
    "address": "TAoLw5yD5XUoHWeBZRSZ1ExK9HMv2CiPvP",
    "name": "Wedding Ryan James;King James Conrad"
  },
  {
    "address": "TBHTJqAy4DhHhmT3dNceJYNRz4SdLofLre",
    "name": "Wang Yunhe 王 云禾;Wan Jack;Wang Jack;Wong Jack;Trafficcash;Trafficcarb;Wilson William"
  },
  {
    "address": "TBcLqqqyZjNj1ptuXFgj5H768NhNU5nDyn",
    "name": "Sokolovski Rolan"
  },
  {
    "address": "TC8axQvzJEVR3NKN6mZnJtGy7537GEmh38",
    "name": "Grinex;Obshchestvo S Ogranichennoi Otvetstvennostyu Grineks"
  },
  {
    "address": "TCFD8N3vM5b4Gr5f1kkajQsodRVNyyAq1d",
    "name": "Old Vector LLC;Obshchestvo S Ogranichennoi Otvetstvennostyu Old Vektor"
  },
  {
    "address": "TCu5onCzXuqxjvVzdB2tR4FLuF66d4yRqf",
    "name": "Sokolovski Rolan"
  },
  {
    "address": "TDFtJtyLPgN3oWUoHh23oJox3T5V5nR11K",
    "name": "Sayyed Sadiq Abbas Habib;Sharma Rakesh;Acosta Jonathan"
  },
  {
    "address": "TEcuHDQthTmULe8fFLUccBPpjfXaTmJuuD",
    "name": "Grinex;Obshchestvo S Ogranichennoi Otvetstvennostyu Grineks"
  },
  {
    "address": "TFdTr9C3BqQrzKBXqSxJfAZFTh8UwBAfSg",
    "name": "OKO DESIGN BUREAU ОКО Конструкторское Бюро"
  },
  {
    "address": "TFwjPScaJRCbSWVAywE1S1WgaUgSnyYUbD",
    "name": "GARANTEX EUROPE OU GARANTEX EUROPE OÜ;Garantex"
  },
  {
    "address": "TGckaiamj5NzaYx6Qp6Zu7kahuHArzUo99",
    "name": "Grinex;Obshchestvo S Ogranichennoi Otvetstvennostyu Grineks"
  },
  {
    "address": "TJkBr9TZ1xBeJoF7RNWqyEMbYqVJ6fXXHR",
    "name": "GARANTEX EUROPE OU GARANTEX EUROPE OÜ;Garantex"
  },
  {
    "address": "TL1k1U6SHohxBqb68kCodxHc9y2LXoDSep",
    "name": "Grinex;Obshchestvo S Ogranichennoi Otvetstvennostyu Grineks"
  },
  {
    "address": "TMStbg5fgb4uTV7fK1gEYF9hKAzP3siPsG",
    "name": "Wang Jiantong 王 建通"
  },
  {
    "address": "TMuCgBejD5RsNANZdjGtaM3YyKGNgDoy7N",
    "name": "Grinex;Obshchestvo S Ogranichennoi Otvetstvennostyu Grineks"
  },
  {
    "address": "TNDjh6WGLYyWmkh8vfu42bXVHUqFNQ3rDq",
    "name": "GARANTEX EUROPE OU GARANTEX EUROPE OÜ;Garantex"
  },
  {
    "address": "TNZxGWCwvsHr6JxQxzoeDXV597Yf7Zb7nV",
    "name": "Grinex;Obshchestvo S Ogranichennoi Otvetstvennostyu Grineks"
  },
  {
    "address": "TNmRfnSUXZoWWzxcDDbf95eGQYXt1mJDt8",
    "name": "Funnull Technology Inc;Funnull;Fang Neng CDN 方能CDN;Funnull LLC;Funnull Inc;Funnull CDN"
  },
  {
    "address": "TPJ1JNX98MJpHueBJeF5SVSg85z8mYg1P1",
    "name": "Wedding Ryan James;King James Conrad"
  },
  {
    "address": "TQ5H49Wz3K57zNHmuXVp6uLzFwitxviABs",
    "name": "ALIVAND Arash Estaki"
  },
  {
    "address": "TRBACioxdrdsYEZHvJWiUDZcMdBPpEe5Ub",
    "name": "Zhang Wei 张 伟"
  },
  {
    "address": "TRakpsE1mZjCUMNPyozR4BW2ZtJsF7ZWFN",
    "name": "ALIVAND Arash Estaki"
  },
  {
    "address": "TSxAAo67VTDgKT537EVXxdogkJtk9c6ojz",
    "name": "DERAKHSHAN Alireza درخشان علیرضا;DERAKHSHAN Alireza Mohammad Javad"
  },
  {
    "address": "TTKnV2S1295UrPr7N67Tp9ykNL7xX2Z4Uj",
    "name": "Xia Fengbing 夏 凤兵"
  },
  {
    "address": "TTUDyVhhpCC1xJoPmWzdjLAzeoPwbSABdr",
    "name": "Cryptex;International Payment Service Provider LLC"
  },
  {
    "address": "TU4tDFRvcKhAZ1jdihojmBWZqvJhQCnJ4F",
    "name": "Aeza Group LLC"
  },
  {
    "address": "TVNyvx2astt2AB1Us67ENjfMZeEXZeiuu6",
    "name": "Wedding Ryan James;King James Conrad"
  },
  {
    "address": "TYDUutYN4YLKUPeT7TG27Yyqw6kNVLq9QZ",
    "name": "ALIVAND Arash Estaki"
  }
]